{"api_utils_index.md":"10e0da56","guide_changelog.md":"4cb90100","components_radio.md":"c9633809","components_pagination.md":"dab4ed1b","api_utils_encrypt.md":"570fc5e3","api_hooks_index.md":"420492f1","api_utils_cookie.md":"16134597","index.md":"d52f7b5b","api_utils_number.md":"0355db65","readme.md":"28e93dd1","api_utils_storage.md":"95787cf5","guide_dev.md":"1ec7252e","guide_quickstart.md":"de5e61dd","api_utils_validate.md":"998e9eba","api_utils_other.md":"f1c69a4d","components_dialog-form.md":"437363e3","guide_installation.md":"24717a62","guide_index.md":"76e550e6","components_page.md":"ccd71db9","components_config.md":"650b1fca","components_drawer-form.md":"ee8f7779","components_description.md":"9f8c0534","api_utils_file.md":"9f900837","guide_i18n.md":"d329f063","api_utils_day.md":"960ceb1c","components_dialog.md":"fea170d0","api_utils_is.md":"36fa62c4","components_type.md":"dd156fc8","components_date-picker.md":"c19d0261","components_search.md":"7a2aab88","components_form.md":"997cd34e","components_table.md":"e52e8290"}
